kaa/__init__.py
kaa/common.py
kaa/debug_entry.py
kaa/errors.py
kaa/kaa_context.py
kaa/metadata.py
kaa/application/__init__.py
kaa/application/adapter/misc_adapter.py
kaa/application/core/idle_mode.py
kaa/application/core/misc_core.py
kaa/application/services/__init__.py
kaa/application/services/config_service.py
kaa/application/services/feedback_service.py
kaa/application/services/produce_solution_service.py
kaa/application/services/task_service.py
kaa/application/services/update_service.py
kaa/application/ui/__init__.py
kaa/application/ui/common.py
kaa/application/ui/facade.py
kaa/application/ui/gradio_view.py
kaa/application/ui/components/alert.py
kaa/application/ui/views/__init__.py
kaa/application/ui/views/feedback_view.py
kaa/application/ui/views/produce_view.py
kaa/application/ui/views/settings_view.py
kaa/application/ui/views/status_view.py
kaa/application/ui/views/task_view.py
kaa/application/ui/views/update_view.py
kaa/config/__init__.py
kaa/config/const.py
kaa/config/produce.py
kaa/config/schema.py
kaa/config/upgrade.py
kaa/config/migrations/__init__.py
kaa/config/migrations/_idol.py
kaa/config/migrations/_v1_to_v2.py
kaa/config/migrations/_v2_to_v3.py
kaa/config/migrations/_v3_to_v4.py
kaa/config/migrations/_v4_to_v5.py
kaa/config/migrations/_v5_to_v6.py
kaa/db/__init__.py
kaa/db/constants.py
kaa/db/drink.py
kaa/db/idol_card.py
kaa/db/sqlite.py
kaa/game_ui/__init__.py
kaa/game_ui/badge.py
kaa/game_ui/common.py
kaa/game_ui/commu_event_buttons.py
kaa/game_ui/dialog.py
kaa/game_ui/drinks_overview.py
kaa/game_ui/idols_overview.py
kaa/game_ui/primary_button.py
kaa/game_ui/schedule.py
kaa/game_ui/scrollable.py
kaa/game_ui/toolbar.py
kaa/image_db/__init__.py
kaa/image_db/db.py
kaa/image_db/descriptors/__init__.py
kaa/image_db/descriptors/hist.py
kaa/main/__init__.py
kaa/main/cli.py
kaa/main/dmm_host.py
kaa/main/gr.py
kaa/main/kaa.py
kaa/resources/__init__.py
kaa/resources/game.db
kaa/resources/game_ver.txt
kaa/resources/__pycache__/__init__.cpython-310.pyc
ksaa-2025.11.post4.dist-info/licenses/LICENSE
ksaa-2025.11.post4.dist-info/METADATA
ksaa-2025.11.post4.dist-info/WHEEL
ksaa-2025.11.post4.dist-info/entry_points.txt
ksaa-2025.11.post4.dist-info/top_level.txt
ksaa-2025.11.post4.dist-info/RECORD
