Metadata-Version: 2.4
Name: ksaa
Version: 2025.11.post4
Summary: Kotones Auto Assistant(kaa) is a script for game 'Gakuen Idol M@ster' that automates the dailies and produces.
Requires-Python: ~=3.10.0
License-File: LICENSE
Requires-Dist: opencv-python~=4.10
Requires-Dist: rapidocr_onnxruntime~=1.4
Requires-Dist: av==14.0.1
Requires-Dist: scikit-image~=0.25
Requires-Dist: thefuzz~=0.22
Requires-Dist: adbutils~=2.8
Requires-Dist: uiautomator2~=3.2
Requires-Dist: fastapi~=0.115.6
Requires-Dist: uvicorn~=0.34.0
Requires-Dist: python-multipart~=0.0.20
Requires-Dist: websockets~=14.1
Requires-Dist: psutil~=6.1
Requires-Dist: gradio~=6.0
Requires-Dist: pydantic~=2.10
Requires-Dist: ksaa-res==0.2.0
Requires-Dist: typing-extensions~=4.12
Requires-Dist: python-dotenv~=1.0.1
Requires-Dist: onnxruntime~=1.14.0
Requires-Dist: numpy<2.0
Requires-Dist: pywin32==310; sys_platform == "win32"
Requires-Dist: ahk~=1.8.3; sys_platform == "win32"
Requires-Dist: win11toast~=0.35; sys_platform == "win32"
Requires-Dist: keyboard~=0.13.5
Requires-Dist: kotonebot[android]==0.5.0
Requires-Dist: kotonebot[windows]==0.5.0; sys_platform == "win32"
Dynamic: license-file
